[
  {
    "id": "vtx_dji_o3_air_unit",
    "manufacturer": "DJI",
    "model": "O3 Air Unit",
    "specs": {
      "system": "DJI O3",
      "type": "Digital HD",
      "max_resolution": "1080p 100fps",
      "recording_resolution": "4K 60fps",
      "latency_ms": 30,
      "max_power_mw": 1200,
      "power_levels_mw": [25, 200, 600, 1200],
      "frequency_band": "5.8GHz",
      "channels": "auto",
      "antenna_connector": "MMCX",
      "antenna_count": 2,
      "voltage_input": "7-26V (2S-6S)",
      "has_camera": true,
      "camera_sensor": "1/2\" CMOS",
      "camera_fov_deg": 155,
      "onboard_storage": "microSD + 20GB internal",
      "gyro_stabilization": true,
      "mounting": "20x20 + side mount"
    },
    "weight_g": 36.3,
    "price_usd": 229.00,
    "category": "digital_hd"
  },
  {
    "id": "vtx_caddx_vista",
    "manufacturer": "Caddx",
    "model": "Vista (DJI Digital FPV System)",
    "specs": {
      "system": "DJI FPV V1",
      "type": "Digital HD",
      "max_resolution": "720p 120fps",
      "recording_resolution": "none (goggles only)",
      "latency_ms": 28,
      "max_power_mw": 700,
      "power_levels_mw": [25, 200, 500, 700],
      "frequency_band": "5.8GHz",
      "channels": 8,
      "antenna_connector": "MMCX",
      "antenna_count": 1,
      "voltage_input": "7-26V (2S-6S)",
      "has_camera": false,
      "camera_compatible": "Nebula series / DJI cam",
      "mounting": "20x20"
    },
    "weight_g": 28.0,
    "price_usd": 149.00,
    "category": "digital_hd"
  },
  {
    "id": "vtx_hdzero_race_v3",
    "manufacturer": "HDZero",
    "model": "Race V3",
    "specs": {
      "system": "HDZero",
      "type": "Digital HD",
      "max_resolution": "1080p 60fps",
      "recording_resolution": "none (goggles DVR)",
      "latency_ms": 22,
      "max_power_mw": 1000,
      "power_levels_mw": [25, 200, 500, 1000],
      "frequency_band": "5.8GHz",
      "channels": 8,
      "antenna_connector": "u.FL (IPEX)",
      "antenna_count": 1,
      "voltage_input": "7-26V (2S-6S)",
      "has_camera": false,
      "camera_compatible": "HDZero Micro V3 / Nano V3",
      "mounting": "20x20"
    },
    "weight_g": 6.2,
    "price_usd": 59.99,
    "category": "digital_hd"
  },
  {
    "id": "vtx_hdzero_whoop_lite",
    "manufacturer": "HDZero",
    "model": "Whoop Lite",
    "specs": {
      "system": "HDZero",
      "type": "Digital HD",
      "max_resolution": "720p 60fps",
      "recording_resolution": "none (goggles DVR)",
      "latency_ms": 22,
      "max_power_mw": 200,
      "power_levels_mw": [25, 200],
      "frequency_band": "5.8GHz",
      "channels": 8,
      "antenna_connector": "u.FL (IPEX)",
      "antenna_count": 1,
      "voltage_input": "3.3-5V",
      "has_camera": false,
      "camera_compatible": "HDZero Nano Lite",
      "mounting": "Whoop AIO compatible"
    },
    "weight_g": 2.0,
    "price_usd": 39.99,
    "category": "digital_hd_micro"
  },
  {
    "id": "vtx_walksnail_avatar_hd_v2",
    "manufacturer": "Walksnail",
    "model": "Avatar HD V2",
    "specs": {
      "system": "Walksnail Avatar",
      "type": "Digital HD",
      "max_resolution": "1080p 60fps",
      "recording_resolution": "1080p 60fps (onboard)",
      "latency_ms": 22,
      "max_power_mw": 1200,
      "power_levels_mw": [25, 200, 500, 1000, 1200],
      "frequency_band": "5.8GHz",
      "channels": "auto",
      "antenna_connector": "u.FL (IPEX)",
      "antenna_count": 2,
      "voltage_input": "7-26V (2S-6S)",
      "has_camera": true,
      "camera_sensor": "1/1.8\" Starlight CMOS",
      "camera_fov_deg": 170,
      "onboard_storage": "8GB + microSD",
      "gyro_stabilization": true,
      "mounting": "20x20 + side mount"
    },
    "weight_g": 33.5,
    "price_usd": 109.99,
    "category": "digital_hd"
  },
  {
    "id": "vtx_rush_tank_ultimate",
    "manufacturer": "Rush",
    "model": "Tank Ultimate Plus 5.8GHz",
    "specs": {
      "system": "Analog",
      "type": "Analog",
      "max_resolution": "NTSC/PAL (depends on camera)",
      "recording_resolution": "none",
      "latency_ms": 10,
      "max_power_mw": 800,
      "power_levels_mw": [25, 200, 400, 800],
      "frequency_band": "5.8GHz",
      "channels": 48,
      "antenna_connector": "MMCX",
      "antenna_count": 1,
      "voltage_input": "5-36V (2S-8S)",
      "has_camera": false,
      "smart_audio": true,
      "pit_mode": true,
      "mounting": "20x20 / 30.5x30.5"
    },
    "weight_g": 7.5,
    "price_usd": 34.99,
    "category": "analog"
  },
  {
    "id": "vtx_tbs_unify_pro32",
    "manufacturer": "TBS",
    "model": "Unify Pro32 HV",
    "specs": {
      "system": "Analog",
      "type": "Analog",
      "max_resolution": "NTSC/PAL (depends on camera)",
      "recording_resolution": "none",
      "latency_ms": 10,
      "max_power_mw": 800,
      "power_levels_mw": [14, 25, 200, 500, 800],
      "frequency_band": "5.8GHz",
      "channels": 40,
      "antenna_connector": "MMCX",
      "antenna_count": 1,
      "voltage_input": "6-25V (2S-6S)",
      "has_camera": false,
      "smart_audio": true,
      "pit_mode": true,
      "mounting": "20x20 / 30.5x30.5"
    },
    "weight_g": 6.0,
    "price_usd": 39.99,
    "category": "analog"
  },
  {
    "id": "vtx_walksnail_avatar_hd_mini",
    "manufacturer": "Walksnail",
    "model": "Avatar HD Mini 1S",
    "specs": {
      "system": "Walksnail Avatar",
      "type": "Digital HD",
      "max_resolution": "720p 60fps",
      "recording_resolution": "720p 60fps (onboard)",
      "latency_ms": 22,
      "max_power_mw": 400,
      "power_levels_mw": [25, 200, 400],
      "frequency_band": "5.8GHz",
      "channels": "auto",
      "antenna_connector": "u.FL (IPEX)",
      "antenna_count": 1,
      "voltage_input": "3.3-5.5V (1S)",
      "has_camera": true,
      "camera_sensor": "1/3\" CMOS",
      "camera_fov_deg": 160,
      "onboard_storage": "8GB",
      "gyro_stabilization": false,
      "mounting": "Whoop compatible"
    },
    "weight_g": 7.5,
    "price_usd": 79.99,
    "category": "digital_hd_micro"
  },
  {
    "id": "vtx_rush_tiny_tank",
    "manufacturer": "Rush",
    "model": "Tiny Tank 5.8GHz",
    "specs": {
      "system": "Analog",
      "type": "Analog",
      "max_resolution": "NTSC/PAL (depends on camera)",
      "recording_resolution": "none",
      "latency_ms": 10,
      "max_power_mw": 350,
      "power_levels_mw": [25, 100, 200, 350],
      "frequency_band": "5.8GHz",
      "channels": 48,
      "antenna_connector": "u.FL (IPEX)",
      "antenna_count": 1,
      "voltage_input": "5V",
      "has_camera": false,
      "smart_audio": true,
      "pit_mode": true,
      "mounting": "16x16 / whoop stack"
    },
    "weight_g": 3.0,
    "price_usd": 19.99,
    "category": "analog_micro"
  }
]
